llm_smart_router-0.1.3.dist-info/licenses/LICENSE
smart_router/__init__.py
smart_router/models.py
smart_router/router.py
smart_router/tool_registry.py
llm_smart_router-0.1.3.dist-info/METADATA
llm_smart_router-0.1.3.dist-info/WHEEL
llm_smart_router-0.1.3.dist-info/top_level.txt
llm_smart_router-0.1.3.dist-info/RECORD
