Metadata-Version: 2.4
Name: llm-smart-router
Version: 0.1.3
Summary: Intelligent tool routing for LLMs with 95.8% reduction in context size
Author-email: LLM Smart Router Contributors <contact@example.com>
License: MIT
Project-URL: Homepage, https://github.com/monsau/llm-smart-router
Project-URL: Documentation, https://llm-smart-router.readthedocs.io
Project-URL: Repository, https://github.com/monsau/llm-smart-router
Project-URL: Issues, https://github.com/monsau/llm-smart-router/issues
Keywords: llm,langchain,ai,routing,tools,agents
Classifier: Development Status :: 4 - Beta
Classifier: Intended Audience :: Developers
Classifier: License :: OSI Approved :: MIT License
Classifier: Programming Language :: Python :: 3
Classifier: Programming Language :: Python :: 3.10
Classifier: Programming Language :: Python :: 3.11
Classifier: Programming Language :: Python :: 3.12
Classifier: Topic :: Software Development :: Libraries :: Python Modules
Classifier: Topic :: Scientific/Engineering :: Artificial Intelligence
Requires-Python: >=3.10
License-File: LICENSE
Requires-Dist: pydantic>=2.0.0
Requires-Dist: langchain>=0.1.0
Requires-Dist: langchain-openai>=0.0.5
Requires-Dist: openai>=1.0.0
Requires-Dist: tiktoken>=0.5.0
Provides-Extra: dev
Requires-Dist: pytest>=7.4.0; extra == "dev"
Requires-Dist: pytest-cov>=4.1.0; extra == "dev"
Requires-Dist: pytest-asyncio>=0.21.0; extra == "dev"
Requires-Dist: mypy>=1.5.0; extra == "dev"
Requires-Dist: ruff>=0.1.0; extra == "dev"
Requires-Dist: pre-commit>=3.4.0; extra == "dev"
Requires-Dist: black>=23.9.0; extra == "dev"
Dynamic: license-file
